README.md
setup.py
XPandas.egg-info/PKG-INFO
XPandas.egg-info/SOURCES.txt
XPandas.egg-info/dependency_links.txt
XPandas.egg-info/not-zip-safe
XPandas.egg-info/top_level.txt
tests/__init__.py
tests/test_bag_of_features.py
tests/test_data_type.py
tests/test_dataframe_transformer.py
tests/test_image_transformers.py
tests/test_transformer.py
tests/test_ts_fresh.py
xpandas/__init__.py
xpandas/data_container/__init__.py
xpandas/data_container/data_container.py
xpandas/transformers/__init__.py
xpandas/transformers/transformer.py
xpandas/transformers/bag_of_features_transformer/__init__.py
xpandas/transformers/bag_of_features_transformer/bag_of_features_transformer.py
xpandas/transformers/identity_transformer/__init__.py
xpandas/transformers/identity_transformer/identity_transformer.py
xpandas/transformers/image_transformer/__init__.py
xpandas/transformers/image_transformer/image_transformer.py
xpandas/transformers/pipeline_transformer/__init__.py
xpandas/transformers/pipeline_transformer/pipeline_transformer.py
xpandas/transformers/series_transformers/__init__.py
xpandas/transformers/series_transformers/series_transformer.py
xpandas/transformers/text_transformer/__init__.py
xpandas/transformers/text_transformer/text_transformer.py